teste/__init__.py
teste/teste.py
felipe_teste-0.0.3.dist-info/LICENSE
felipe_teste-0.0.3.dist-info/METADATA
felipe_teste-0.0.3.dist-info/WHEEL
felipe_teste-0.0.3.dist-info/top_level.txt
felipe_teste-0.0.3.dist-info/RECORD
